{
  "Light": {
    "center": {
      "x": 465.12375,
      "y": 732.74524
    },
    "height": 0.0,
    "falloff_radius": 80.0,
    "falloff_power": 2.0,
    "state_u32": 0,
    "state": 0.0,
    "color": "#ff00ffff",
    "color2": "#00000000",
    "is_timer_enabled": false,
    "timer_interval": 100,
    "blink_pattern": "Inserts",
    "off_image": "pf",
    "blink_interval": 1250,
    "intensity": 4.0,
    "transmission_scale": 0.0,
    "surface": "",
    "name": "L20",
    "is_backglass": false,
    "depth_bias": 0.0,
    "fade_speed_up": 0.04,
    "fade_speed_down": 0.04,
    "is_bulb_light": true,
    "is_image_mode": false,
    "show_bulb_mesh": false,
    "has_static_bulb_mesh": true,
    "show_reflection_on_ball": true,
    "mesh_radius": 20.0,
    "bulb_modulate_vs_add": 1.0,
    "bulb_halo_height": -1.0,
    "shadows": "none",
    "fader": "none",
    "visible": true,
    "drag_points": [
      {
        "x": 517.4765,
        "y": 682.27136,
        "z": 0.0,
        "smooth": true,
        "is_slingshot": false,
        "has_auto_texture": true,
        "tex_coord": 0.0,
        "is_locked": false,
        "editor_layer": 0,
        "editor_layer_name": "",
        "editor_layer_visibility": true
      },
      {
        "x": 512.06104,
        "y": 683.1575,
        "z": 0.0,
        "smooth": false,
        "is_slingshot": false,
        "has_auto_texture": true,
        "tex_coord": 0.0,
        "is_locked": false,
        "editor_layer": 0,
        "editor_layer_name": "",
        "editor_layer_visibility": true
      },
      {
        "x": 475.63992,
        "y": 714.6942,
        "z": 0.0,
        "smooth": false,
        "is_slingshot": false,
        "has_auto_texture": true,
        "tex_coord": 0.0,
        "is_locked": false,
        "editor_layer": 0,
        "editor_layer_name": "",
        "editor_layer_visibility": true
      },
      {
        "x": 471.12103,
        "y": 717.7557,
        "z": 0.0,
        "smooth": true,
        "is_slingshot": false,
        "has_auto_texture": true,
        "tex_coord": 0.0,
        "is_locked": false,
        "editor_layer": 0,
        "editor_layer_name": "",
        "editor_layer_visibility": true
      },
      {
        "x": 467.69162,
        "y": 714.1978,
        "z": 0.0,
        "smooth": true,
        "is_slingshot": false,
        "has_auto_texture": true,
        "tex_coord": 0.0,
        "is_locked": false,
        "editor_layer": 0,
        "editor_layer_name": "",
        "editor_layer_visibility": true
      },
      {
        "x": 466.9467,
        "y": 708.9354,
        "z": 0.0,
        "smooth": true,
        "is_slingshot": false,
        "has_auto_texture": true,
        "tex_coord": 0.0,
        "is_locked": false,
        "editor_layer": 0,
        "editor_layer_name": "",
        "editor_layer_visibility": true
      },
      {
        "x": 461.2744,
        "y": 706.5073,
        "z": 0.0,
        "smooth": true,
        "is_slingshot": false,
        "has_auto_texture": true,
        "tex_coord": 0.0,
        "is_locked": false,
        "editor_layer": 0,
        "editor_layer_name": "",
        "editor_layer_visibility": true
      },
      {
        "x": 456.6386,
        "y": 709.5064,
        "z": 0.0,
        "smooth": false,
        "is_slingshot": false,
        "has_auto_texture": true,
        "tex_coord": 0.0,
        "is_locked": false,
        "editor_layer": 0,
        "editor_layer_name": "",
        "editor_layer_visibility": true
      },
      {
        "x": 414.38715,
        "y": 769.951,
        "z": 0.0,
        "smooth": false,
        "is_slingshot": false,
        "has_auto_texture": true,
        "tex_coord": 0.0,
        "is_locked": false,
        "editor_layer": 0,
        "editor_layer_name": "",
        "editor_layer_visibility": true
      },
      {
        "x": 411.64954,
        "y": 776.6794,
        "z": 0.0,
        "smooth": true,
        "is_slingshot": false,
        "has_auto_texture": true,
        "tex_coord": 0.0,
        "is_locked": false,
        "editor_layer": 0,
        "editor_layer_name": "",
        "editor_layer_visibility": true
      },
      {
        "x": 418.2134,
        "y": 781.2401,
        "z": 0.0,
        "smooth": false,
        "is_slingshot": false,
        "has_auto_texture": true,
        "tex_coord": 0.0,
        "is_locked": false,
        "editor_layer": 0,
        "editor_layer_name": "",
        "editor_layer_visibility": true
      },
      {
        "x": 426.05905,
        "y": 776.2846,
        "z": 0.0,
        "smooth": false,
        "is_slingshot": false,
        "has_auto_texture": true,
        "tex_coord": 0.0,
        "is_locked": false,
        "editor_layer": 0,
        "editor_layer_name": "",
        "editor_layer_visibility": true
      },
      {
        "x": 455.4289,
        "y": 749.89734,
        "z": 0.0,
        "smooth": false,
        "is_slingshot": false,
        "has_auto_texture": true,
        "tex_coord": 0.0,
        "is_locked": false,
        "editor_layer": 0,
        "editor_layer_name": "",
        "editor_layer_visibility": true
      },
      {
        "x": 459.28683,
        "y": 746.5047,
        "z": 0.0,
        "smooth": true,
        "is_slingshot": false,
        "has_auto_texture": true,
        "tex_coord": 0.0,
        "is_locked": false,
        "editor_layer": 0,
        "editor_layer_name": "",
        "editor_layer_visibility": true
      },
      {
        "x": 463.33612,
        "y": 746.8602,
        "z": 0.0,
        "smooth": true,
        "is_slingshot": false,
        "has_auto_texture": true,
        "tex_coord": 0.0,
        "is_locked": false,
        "editor_layer": 0,
        "editor_layer_name": "",
        "editor_layer_visibility": true
      },
      {
        "x": 466.8661,
        "y": 752.74384,
        "z": 0.0,
        "smooth": true,
        "is_slingshot": false,
        "has_auto_texture": true,
        "tex_coord": 0.0,
        "is_locked": false,
        "editor_layer": 0,
        "editor_layer_name": "",
        "editor_layer_visibility": true
      },
      {
        "x": 471.65048,
        "y": 756.3636,
        "z": 0.0,
        "smooth": true,
        "is_slingshot": false,
        "has_auto_texture": true,
        "tex_coord": 0.0,
        "is_locked": false,
        "editor_layer": 0,
        "editor_layer_name": "",
        "editor_layer_visibility": true
      },
      {
        "x": 476.6731,
        "y": 752.1555,
        "z": 0.0,
        "smooth": false,
        "is_slingshot": false,
        "has_auto_texture": true,
        "tex_coord": 0.0,
        "is_locked": false,
        "editor_layer": 0,
        "editor_layer_name": "",
        "editor_layer_visibility": true
      },
      {
        "x": 517.2983,
        "y": 693.7015,
        "z": 0.0,
        "smooth": false,
        "is_slingshot": false,
        "has_auto_texture": true,
        "tex_coord": 0.0,
        "is_locked": false,
        "editor_layer": 0,
        "editor_layer_name": "",
        "editor_layer_visibility": true
      },
      {
        "x": 521.2551,
        "y": 687.65424,
        "z": 0.0,
        "smooth": true,
        "is_slingshot": false,
        "has_auto_texture": true,
        "tex_coord": 0.0,
        "is_locked": false,
        "editor_layer": 0,
        "editor_layer_name": "",
        "editor_layer_visibility": true
      }
    ]
  }
}