{
  "Light": {
    "center": {
      "x": 136.60234,
      "y": 34.114105
    },
    "height": 301.0,
    "falloff_radius": 20.0,
    "falloff_power": 1.0,
    "state_u32": 2,
    "state": 2.0,
    "color": "#00000000",
    "color2": "#00000000",
    "is_timer_enabled": false,
    "timer_interval": 100,
    "blink_pattern": "tScoreSegs",
    "off_image": "",
    "blink_interval": 125,
    "intensity": 300.0,
    "transmission_scale": 0.5,
    "surface": "",
    "name": "p1_seg81",
    "is_backglass": true,
    "depth_bias": 0.0,
    "fade_speed_up": 1.5,
    "fade_speed_down": 0.6,
    "is_bulb_light": true,
    "is_image_mode": false,
    "show_bulb_mesh": false,
    "has_static_bulb_mesh": true,
    "show_reflection_on_ball": false,
    "mesh_radius": 20.0,
    "bulb_modulate_vs_add": 0.9,
    "bulb_halo_height": 300.0,
    "shadows": "none",
    "fader": "none",
    "visible": true,
    "drag_points": [
      {
        "x": 137.99176,
        "y": 29.926256,
        "z": 0.0,
        "smooth": false,
        "is_slingshot": false,
        "has_auto_texture": true,
        "tex_coord": 0.0,
        "is_locked": false,
        "editor_layer": 0,
        "editor_layer_name": "",
        "editor_layer_visibility": true
      },
      {
        "x": 137.26073,
        "y": 29.086395,
        "z": 0.0,
        "smooth": false,
        "is_slingshot": false,
        "has_auto_texture": true,
        "tex_coord": 0.0,
        "is_locked": false,
        "editor_layer": 0,
        "editor_layer_name": "",
        "editor_layer_visibility": true
      },
      {
        "x": 136.24117,
        "y": 30.199038,
        "z": 0.0,
        "smooth": false,
        "is_slingshot": false,
        "has_auto_texture": true,
        "tex_coord": 0.0,
        "is_locked": false,
        "editor_layer": 0,
        "editor_layer_name": "",
        "editor_layer_visibility": true
      },
      {
        "x": 135.15851,
        "y": 37.06197,
        "z": 0.0,
        "smooth": false,
        "is_slingshot": false,
        "has_auto_texture": true,
        "tex_coord": 0.0,
        "is_locked": false,
        "editor_layer": 0,
        "editor_layer_name": "",
        "editor_layer_visibility": true
      },
      {
        "x": 135.95062,
        "y": 38.170216,
        "z": 0.0,
        "smooth": false,
        "is_slingshot": false,
        "has_auto_texture": true,
        "tex_coord": 0.0,
        "is_locked": false,
        "editor_layer": 0,
        "editor_layer_name": "",
        "editor_layer_visibility": true
      },
      {
        "x": 137.02095,
        "y": 37.66965,
        "z": 0.0,
        "smooth": false,
        "is_slingshot": false,
        "has_auto_texture": true,
        "tex_coord": 0.0,
        "is_locked": false,
        "editor_layer": 0,
        "editor_layer_name": "",
        "editor_layer_visibility": true
      }
    ]
  }
}