[
  {
    "name": "Rubbers",
    "items": [
      "Rubber4",
      "LSling",
      "RSling",
      "RubberBand002",
      "zCol_Rubber_Sleeve002",
      "zCol_Rubber_Post008",
      "zCol_Rubber_Post007",
      "zCol_Rubber_Peg007",
      "zCol_Rubber_Peg006",
      "zCol_Rubber_Peg005",
      "zCol_Rubber_Peg002",
      "zCol_Rubber_Post035",
      "zCol_Rubber_Post032",
      "zCol_Rubber_Post031",
      "zCol_Rubber_Post030",
      "zCol_Rubber_Post029",
      "zCol_Rubber_Post028",
      "zCol_Rubber_Post027",
      "zCol_Rubber_Post024",
      "zCol_Rubber_Post023",
      "zCol_Rubber_Post022",
      "zCol_Rubber_Post021",
      "zCol_Rubber_Post020",
      "zCol_Rubber_Post019",
      "zCol_Rubber_Post018",
      "zCol_Rubber_Post017",
      "zCol_Rubber_Post016",
      "zCol_Rubber_Post015",
      "zCol_Rubber_Post014",
      "zCol_Rubber_Post013",
      "zCol_Rubber_Post012",
      "zCol_Rubber_Post011",
      "zCol_Rubber_Sleeve001",
      "zCol_Rubber_Post003",
      "zCol_Rubber_Sleeve003",
      "zCol_Rubber_Peg004",
      "zCol_Rubber_Peg003",
      "zCol_Rubber_Post006",
      "zCol_Rubber_Post005",
      "zCol_Rubber_rightsling",
      "zCol_Rubber_leftsling",
      "zCol_Rubber_Post002",
      "zCol_Rubber_Post001",
      "zCol_Rubber_Post034",
      "zCol_Rubber_Post033",
      "zCol_Rubber_Post010",
      "zCol_Rubber_Post009",
      "zCol_Rubber_Post004",
      "RubberBand011",
      "RubberBand010",
      "RubberBand009",
      "RubberBand008",
      "RubberBand007",
      "RubberBand005",
      "RubberBand004",
      "RubberBand003",
      "Wall005",
      "RubberBand001",
      "RubberBand006",
      "zCol_Rubber_Post025",
      "RubberBand012"
    ],
    "fire_events": true,
    "stop_single_events": false,
    "group_elements": false
  },
  {
    "name": "Targets",
    "items": [
      "s_ST2",
      "s_ST1",
      "s_ST3",
      "s_ST4"
    ],
    "fire_events": true,
    "stop_single_events": false,
    "group_elements": false
  },
  {
    "name": "Metals",
    "items": [
      "Wall18",
      "Wall004",
      "Wall5",
      "Wall20",
      "Wall21",
      "Wall17",
      "Wall16",
      "Wall14",
      "Wall010",
      "DiverterWall1",
      "Wall011"
    ],
    "fire_events": true,
    "stop_single_events": false,
    "group_elements": false
  },
  {
    "name": "Gates",
    "items": [],
    "fire_events": true,
    "stop_single_events": false,
    "group_elements": false
  },
  {
    "name": "GatesWire",
    "items": [
      "Gate"
    ],
    "fire_events": true,
    "stop_single_events": false,
    "group_elements": false
  },
  {
    "name": "Apron",
    "items": [
      "Wall001",
      "Wall78"
    ],
    "fire_events": true,
    "stop_single_events": false,
    "group_elements": false
  },
  {
    "name": "Walls",
    "items": [
      "plastic5",
      "Wall5top",
      "Wall350",
      "Wall3",
      "Wall4"
    ],
    "fire_events": true,
    "stop_single_events": false,
    "group_elements": false
  },
  {
    "name": "Rollovers",
    "items": [
      "s_Plunger1",
      "s_RightOrb1",
      "s_LeftOrb2",
      "s_LeftOrb1",
      "s_LeftInOutlane",
      "s_RightOutlane",
      "s_TopLane4",
      "s_TopLane3",
      "s_TopLane2",
      "s_TopLane1",
      "s_RightInlane",
      "s_LeftInlane",
      "s_RightOrb2"
    ],
    "fire_events": true,
    "stop_single_events": false,
    "group_elements": false
  },
  {
    "name": "dPosts",
    "items": [
      "zCol_Rubber_Post034",
      "zCol_Rubber_Post027",
      "zCol_Rubber_Post024",
      "zCol_Rubber_Peg002",
      "zCol_Rubber_Post023",
      "zCol_Rubber_Post022",
      "zCol_Rubber_Post021",
      "zCol_Rubber_Post020",
      "zCol_Rubber_Post018",
      "zCol_Rubber_Post019",
      "zCol_Rubber_Post017",
      "zCol_Rubber_Post016",
      "zCol_Rubber_Peg006",
      "zCol_Rubber_Peg005",
      "zCol_Rubber_Post015",
      "zCol_Rubber_Post014",
      "zCol_Rubber_Post033",
      "zCol_Rubber_Post011",
      "zCol_Rubber_Post012",
      "zCol_Rubber_Post013",
      "zCol_Rubber_Post004",
      "zCol_Rubber_Post003",
      "zCol_Rubber_Peg007",
      "zCol_Rubber_Post031",
      "zCol_Rubber_Post030",
      "zCol_Rubber_Post029",
      "zCol_Rubber_Post028",
      "zCol_Rubber_Post032",
      "zCol_Rubber_Post035",
      "zCol_Rubber_Post009",
      "zCol_Rubber_Peg003",
      "zCol_Rubber_Post010",
      "zCol_Rubber_Post005",
      "zCol_Rubber_Post006",
      "zCol_Rubber_Post002",
      "zCol_Rubber_Post001",
      "zCol_Rubber_Peg004",
      "zCol_Rubber_Post007",
      "zCol_Rubber_Post008",
      "zCol_Rubber_Post025"
    ],
    "fire_events": true,
    "stop_single_events": false,
    "group_elements": false
  },
  {
    "name": "dSleeves",
    "items": [
      "zCol_Rubber_Sleeve003",
      "zCol_Rubber_Sleeve002"
    ],
    "fire_events": true,
    "stop_single_events": false,
    "group_elements": false
  },
  {
    "name": "VR_Cab",
    "items": [
      "PinCab_Back",
      "PinCab_Coindoor",
      "PinCab_Backbox",
      "PinCab_Buttons",
      "PinCab_Cabinet",
      "PinCab_Metals",
      "PinCab_Shooter",
      "PinCab_Housing",
      "PinCab_Bottom",
      "PinCab_Blades",
      "PinCab_Rails"
    ],
    "fire_events": false,
    "stop_single_events": false,
    "group_elements": false
  },
  {
    "name": "TargetBounce",
    "items": [
      "STBlocker2",
      "STBlocker1",
      "aDT1",
      "aDT2",
      "aDT3",
      "aDT4",
      "aDT5",
      "aDT6"
    ],
    "fire_events": true,
    "stop_single_events": false,
    "group_elements": false
  },
  {
    "name": "glf_lights",
    "items": [
      "ball_seg18",
      "p4_seg120",
      "p4_seg119",
      "p4_seg118",
      "p4_seg117",
      "p4_seg116",
      "p4_seg115",
      "p4_seg114",
      "p4_seg113",
      "p4_seg112",
      "p4_seg111",
      "p4_seg110",
      "p4_seg109",
      "p4_seg108",
      "p4_seg107",
      "p4_seg106",
      "p3_seg120",
      "p3_seg119",
      "p3_seg118",
      "p3_seg117",
      "p3_seg116",
      "p3_seg115",
      "p3_seg114",
      "p3_seg113",
      "p3_seg112",
      "p3_seg111",
      "p3_seg110",
      "p3_seg109",
      "p3_seg108",
      "p3_seg107",
      "p3_seg106",
      "p2_seg120",
      "p2_seg119",
      "p2_seg118",
      "p2_seg117",
      "p2_seg116",
      "p2_seg115",
      "p2_seg114",
      "p2_seg113",
      "p2_seg112",
      "p2_seg111",
      "p2_seg110",
      "p2_seg109",
      "p2_seg108",
      "p2_seg107",
      "p2_seg106",
      "p1_seg120",
      "p1_seg119",
      "p1_seg118",
      "p1_seg117",
      "p1_seg116",
      "p1_seg115",
      "p1_seg114",
      "p1_seg113",
      "p1_seg112",
      "p1_seg111",
      "p1_seg110",
      "p1_seg109",
      "p1_seg108",
      "p1_seg107",
      "p1_seg106",
      "p4_seg105",
      "p3_seg105",
      "p2_seg105",
      "p4_seg104",
      "p3_seg104",
      "p2_seg104",
      "p4_seg103",
      "p3_seg103",
      "p2_seg103",
      "p4_seg102",
      "p3_seg102",
      "p2_seg102",
      "p4_seg101",
      "p3_seg101",
      "p2_seg101",
      "p4_seg100",
      "p3_seg100",
      "p2_seg100",
      "p4_seg99",
      "p3_seg99",
      "p2_seg99",
      "p4_seg98",
      "p3_seg98",
      "p2_seg98",
      "p4_seg97",
      "p3_seg97",
      "p2_seg97",
      "p4_seg96",
      "p3_seg96",
      "p2_seg96",
      "p4_seg95",
      "p3_seg95",
      "p2_seg95",
      "p4_seg94",
      "p3_seg94",
      "p2_seg94",
      "p4_seg93",
      "p3_seg93",
      "p2_seg93",
      "p4_seg92",
      "p3_seg92",
      "p2_seg92",
      "p4_seg91",
      "p3_seg91",
      "p2_seg91",
      "p4_seg90",
      "p3_seg90",
      "p2_seg90",
      "p4_seg89",
      "p3_seg89",
      "p2_seg89",
      "p4_seg88",
      "p3_seg88",
      "p2_seg88",
      "p4_seg87",
      "p3_seg87",
      "p2_seg87",
      "p4_seg86",
      "p3_seg86",
      "p2_seg86",
      "p4_seg85",
      "p3_seg85",
      "p2_seg85",
      "p4_seg84",
      "p3_seg84",
      "p2_seg84",
      "p4_seg83",
      "p3_seg83",
      "p2_seg83",
      "p4_seg82",
      "p3_seg82",
      "p2_seg82",
      "p4_seg81",
      "p3_seg81",
      "p2_seg81",
      "p4_seg80",
      "p3_seg80",
      "p2_seg80",
      "p4_seg79",
      "p3_seg79",
      "p2_seg79",
      "p4_seg78",
      "p3_seg78",
      "p2_seg78",
      "p4_seg77",
      "p3_seg77",
      "p2_seg77",
      "p4_seg76",
      "p3_seg76",
      "p2_seg76",
      "p4_seg75",
      "p3_seg75",
      "p2_seg75",
      "p4_seg74",
      "p3_seg74",
      "p2_seg74",
      "p4_seg73",
      "p3_seg73",
      "p2_seg73",
      "p4_seg72",
      "p3_seg72",
      "p2_seg72",
      "p4_seg71",
      "p3_seg71",
      "p2_seg71",
      "p4_seg70",
      "p3_seg70",
      "p2_seg70",
      "p4_seg69",
      "p3_seg69",
      "p2_seg69",
      "p4_seg68",
      "p3_seg68",
      "p2_seg68",
      "p4_seg67",
      "p3_seg67",
      "p2_seg67",
      "p4_seg66",
      "p3_seg66",
      "p2_seg66",
      "p4_seg65",
      "p3_seg65",
      "p2_seg65",
      "p4_seg64",
      "p3_seg64",
      "p2_seg64",
      "p4_seg63",
      "p3_seg63",
      "p2_seg63",
      "p4_seg62",
      "p3_seg62",
      "p2_seg62",
      "p4_seg61",
      "p3_seg61",
      "p2_seg61",
      "p4_seg60",
      "p3_seg60",
      "p2_seg60",
      "p4_seg59",
      "p3_seg59",
      "p2_seg59",
      "p4_seg58",
      "p3_seg58",
      "p2_seg58",
      "p4_seg57",
      "p3_seg57",
      "p2_seg57",
      "p4_seg56",
      "p3_seg56",
      "p2_seg56",
      "p4_seg55",
      "p3_seg55",
      "p2_seg55",
      "p4_seg54",
      "p3_seg54",
      "p2_seg54",
      "p4_seg53",
      "p3_seg53",
      "p2_seg53",
      "p4_seg52",
      "p3_seg52",
      "p2_seg52",
      "p4_seg51",
      "p3_seg51",
      "p2_seg51",
      "p4_seg50",
      "p3_seg50",
      "p2_seg50",
      "p4_seg49",
      "p3_seg49",
      "p2_seg49",
      "p4_seg48",
      "p3_seg48",
      "p2_seg48",
      "p4_seg47",
      "p3_seg47",
      "p2_seg47",
      "p4_seg46",
      "p3_seg46",
      "p2_seg46",
      "p4_seg45",
      "p3_seg45",
      "p2_seg45",
      "p4_seg44",
      "p3_seg44",
      "p2_seg44",
      "p4_seg43",
      "p3_seg43",
      "p2_seg43",
      "p4_seg42",
      "p3_seg42",
      "p2_seg42",
      "p4_seg41",
      "p3_seg41",
      "p2_seg41",
      "p4_seg40",
      "p3_seg40",
      "p2_seg40",
      "p4_seg39",
      "p3_seg39",
      "p2_seg39",
      "p4_seg38",
      "p3_seg38",
      "p2_seg38",
      "p4_seg37",
      "p3_seg37",
      "p2_seg37",
      "p4_seg36",
      "p3_seg36",
      "p2_seg36",
      "p4_seg35",
      "p3_seg35",
      "p2_seg35",
      "p4_seg34",
      "p3_seg34",
      "p2_seg34",
      "p4_seg33",
      "p3_seg33",
      "p2_seg33",
      "p4_seg32",
      "p3_seg32",
      "p2_seg32",
      "p4_seg31",
      "p3_seg31",
      "p2_seg31",
      "p4_seg30",
      "p3_seg30",
      "p2_seg30",
      "p4_seg29",
      "p3_seg29",
      "p2_seg29",
      "p4_seg28",
      "p3_seg28",
      "p2_seg28",
      "p4_seg27",
      "p3_seg27",
      "p2_seg27",
      "p4_seg26",
      "p3_seg26",
      "p2_seg26",
      "p4_seg25",
      "p3_seg25",
      "p2_seg25",
      "p4_seg24",
      "p3_seg24",
      "p2_seg24",
      "p4_seg23",
      "p3_seg23",
      "p2_seg23",
      "p4_seg22",
      "p3_seg22",
      "p2_seg22",
      "p4_seg21",
      "p3_seg21",
      "p2_seg21",
      "p4_seg20",
      "p3_seg20",
      "p2_seg20",
      "p4_seg19",
      "p3_seg19",
      "p2_seg19",
      "p4_seg18",
      "p3_seg18",
      "p2_seg18",
      "p4_seg17",
      "p3_seg17",
      "p2_seg17",
      "p4_seg16",
      "p3_seg16",
      "p2_seg16",
      "p4_seg15",
      "p3_seg15",
      "p2_seg15",
      "p4_seg14",
      "p3_seg14",
      "p2_seg14",
      "p4_seg13",
      "p3_seg13",
      "p2_seg13",
      "p4_seg12",
      "p3_seg12",
      "p2_seg12",
      "p4_seg11",
      "p3_seg11",
      "p2_seg11",
      "p4_seg10",
      "p3_seg10",
      "p2_seg10",
      "p4_seg9",
      "p3_seg9",
      "p2_seg9",
      "p4_seg8",
      "p3_seg8",
      "p2_seg8",
      "p4_seg7",
      "p3_seg7",
      "p2_seg7",
      "p4_seg6",
      "p3_seg6",
      "p2_seg6",
      "p4_seg5",
      "p3_seg5",
      "p2_seg5",
      "p4_seg4",
      "p3_seg4",
      "p2_seg4",
      "p4_seg3",
      "p3_seg3",
      "p2_seg3",
      "p4_seg2",
      "p3_seg2",
      "p2_seg2",
      "p4_seg1",
      "p3_seg1",
      "p2_seg1",
      "ball_seg30",
      "ball_seg29",
      "ball_seg28",
      "ball_seg27",
      "ball_seg26",
      "ball_seg25",
      "ball_seg24",
      "ball_seg23",
      "ball_seg22",
      "ball_seg21",
      "ball_seg20",
      "ball_seg19",
      "ball_seg17",
      "ball_seg16",
      "ball_seg15",
      "ball_seg14",
      "ball_seg13",
      "ball_seg12",
      "ball_seg11",
      "ball_seg10",
      "ball_seg9",
      "ball_seg8",
      "ball_seg7",
      "ball_seg6",
      "ball_seg5",
      "ball_seg4",
      "ball_seg3",
      "ball_seg2",
      "ball_seg1",
      "p1_seg105",
      "p1_seg104",
      "p1_seg103",
      "p1_seg102",
      "p1_seg101",
      "p1_seg100",
      "p1_seg99",
      "p1_seg98",
      "p1_seg97",
      "p1_seg96",
      "p1_seg95",
      "p1_seg94",
      "p1_seg93",
      "p1_seg92",
      "p1_seg91",
      "p1_seg90",
      "p1_seg89",
      "p1_seg88",
      "p1_seg87",
      "p1_seg86",
      "p1_seg85",
      "p1_seg84",
      "p1_seg83",
      "p1_seg82",
      "p1_seg81",
      "p1_seg80",
      "p1_seg79",
      "p1_seg78",
      "p1_seg77",
      "p1_seg76",
      "p1_seg75",
      "p1_seg74",
      "p1_seg73",
      "p1_seg72",
      "p1_seg71",
      "p1_seg70",
      "p1_seg69",
      "p1_seg68",
      "p1_seg67",
      "p1_seg66",
      "p1_seg65",
      "p1_seg64",
      "p1_seg63",
      "p1_seg62",
      "p1_seg61",
      "p1_seg60",
      "p1_seg59",
      "p1_seg58",
      "p1_seg57",
      "p1_seg56",
      "p1_seg55",
      "p1_seg54",
      "p1_seg53",
      "p1_seg52",
      "p1_seg51",
      "p1_seg50",
      "p1_seg49",
      "p1_seg48",
      "p1_seg47",
      "p1_seg46",
      "p1_seg45",
      "p1_seg44",
      "p1_seg43",
      "p1_seg42",
      "p1_seg41",
      "p1_seg40",
      "p1_seg39",
      "p1_seg38",
      "p1_seg37",
      "p1_seg36",
      "p1_seg35",
      "p1_seg34",
      "p1_seg33",
      "p1_seg32",
      "p1_seg31",
      "p1_seg30",
      "p1_seg29",
      "p1_seg28",
      "p1_seg27",
      "p1_seg26",
      "p1_seg25",
      "p1_seg24",
      "p1_seg23",
      "p1_seg22",
      "p1_seg21",
      "p1_seg20",
      "p1_seg19",
      "p1_seg18",
      "p1_seg17",
      "p1_seg16",
      "p1_seg15",
      "p1_seg14",
      "p1_seg13",
      "p1_seg12",
      "p1_seg11",
      "p1_seg10",
      "p1_seg9",
      "p1_seg8",
      "p1_seg7",
      "p1_seg6",
      "p1_seg5",
      "p1_seg4",
      "p1_seg3",
      "p1_seg2",
      "p1_seg1",
      "gi018",
      "gi001",
      "gi022",
      "gi024",
      "gi021",
      "gi020",
      "gi019",
      "gi017",
      "gi016",
      "gi015",
      "gi014",
      "gi013",
      "gi012",
      "gi011",
      "gi010",
      "gi009",
      "gi008",
      "gi007",
      "gi006",
      "gi050",
      "BL1a",
      "L18",
      "L14",
      "L15",
      "L17",
      "L13",
      "L12",
      "L11",
      "L19",
      "L24",
      "L09",
      "L25",
      "L20",
      "L04",
      "L01",
      "L02",
      "L03",
      "L07",
      "L08",
      "L23",
      "L32",
      "L10",
      "L16",
      "L28",
      "L29",
      "L30",
      "L31",
      "L05",
      "L06",
      "L26",
      "L27",
      "L22",
      "L21",
      "FL2",
      "FL3",
      "FL1",
      "FL4",
      "BL2a",
      "BL3",
      "BL2",
      "BL1",
      "BL3a",
      "L33",
      "L34",
      "L35",
      "L36",
      "L37",
      "L38",
      "L39"
    ],
    "fire_events": false,
    "stop_single_events": false,
    "group_elements": false
  },
  {
    "name": "glf_switches",
    "items": [
      "s_Bumper3",
      "s_Bumper2",
      "s_Bumper1",
      "s_Plunger1",
      "s_RightOrb1",
      "s_LeftOrb2",
      "s_LeftOrb1",
      "s_LeftInOutlane",
      "s_RightOutlane",
      "s_TopLane4",
      "s_TopLane3",
      "s_TopLane2",
      "s_TopLane1",
      "s_RightInlane",
      "s_LeftInlane",
      "s_Kicker1",
      "s_Kicker2",
      "s_RightOrb2"
    ],
    "fire_events": false,
    "stop_single_events": false,
    "group_elements": false
  },
  {
    "name": "glf_slingshots",
    "items": [
      "s_LeftSlingshot",
      "s_RightSlingshot"
    ],
    "fire_events": false,
    "stop_single_events": false,
    "group_elements": false
  },
  {
    "name": "glf_spinners",
    "items": [
      "s_spinner"
    ],
    "fire_events": false,
    "stop_single_events": false,
    "group_elements": false
  },
  {
    "name": "VR_MinRoom",
    "items": [
      "VR_Wall_Right",
      "VR_Floor",
      "VR_Roof",
      "VR_Wall_Left"
    ],
    "fire_events": false,
    "stop_single_events": false,
    "group_elements": false
  },
  {
    "name": "DesktopLights",
    "items": [
      "ball_seg18",
      "p4_seg120",
      "p4_seg119",
      "p4_seg118",
      "p4_seg117",
      "p4_seg116",
      "p4_seg115",
      "p4_seg114",
      "p4_seg113",
      "p4_seg112",
      "p4_seg111",
      "p4_seg110",
      "p4_seg109",
      "p4_seg108",
      "p4_seg107",
      "p4_seg106",
      "p3_seg120",
      "p3_seg119",
      "p3_seg118",
      "p3_seg117",
      "p3_seg116",
      "p3_seg115",
      "p3_seg114",
      "p3_seg113",
      "p3_seg112",
      "p3_seg111",
      "p3_seg110",
      "p3_seg109",
      "p3_seg108",
      "p3_seg107",
      "p3_seg106",
      "p2_seg120",
      "p2_seg119",
      "p2_seg118",
      "p2_seg117",
      "p2_seg116",
      "p2_seg115",
      "p2_seg114",
      "p2_seg113",
      "p2_seg112",
      "p2_seg111",
      "p2_seg110",
      "p2_seg109",
      "p2_seg108",
      "p2_seg107",
      "p2_seg106",
      "p1_seg120",
      "p1_seg119",
      "p1_seg118",
      "p1_seg117",
      "p1_seg116",
      "p1_seg115",
      "p1_seg114",
      "p1_seg113",
      "p1_seg112",
      "p1_seg111",
      "p1_seg110",
      "p1_seg109",
      "p1_seg108",
      "p1_seg107",
      "p1_seg106",
      "p4_seg105",
      "p3_seg105",
      "p2_seg105",
      "p4_seg104",
      "p3_seg104",
      "p2_seg104",
      "p4_seg103",
      "p3_seg103",
      "p2_seg103",
      "p4_seg102",
      "p3_seg102",
      "p2_seg102",
      "p4_seg101",
      "p3_seg101",
      "p2_seg101",
      "p4_seg100",
      "p3_seg100",
      "p2_seg100",
      "p4_seg99",
      "p3_seg99",
      "p2_seg99",
      "p4_seg98",
      "p3_seg98",
      "p2_seg98",
      "p4_seg97",
      "p3_seg97",
      "p2_seg97",
      "p4_seg96",
      "p3_seg96",
      "p2_seg96",
      "p4_seg95",
      "p3_seg95",
      "p2_seg95",
      "p4_seg94",
      "p3_seg94",
      "p2_seg94",
      "p4_seg93",
      "p3_seg93",
      "p2_seg93",
      "p4_seg92",
      "p3_seg92",
      "p2_seg92",
      "p4_seg91",
      "p3_seg91",
      "p2_seg91",
      "p4_seg90",
      "p3_seg90",
      "p2_seg90",
      "p4_seg89",
      "p3_seg89",
      "p2_seg89",
      "p4_seg88",
      "p3_seg88",
      "p2_seg88",
      "p4_seg87",
      "p3_seg87",
      "p2_seg87",
      "p4_seg86",
      "p3_seg86",
      "p2_seg86",
      "p4_seg85",
      "p3_seg85",
      "p2_seg85",
      "p4_seg84",
      "p3_seg84",
      "p2_seg84",
      "p4_seg83",
      "p3_seg83",
      "p2_seg83",
      "p4_seg82",
      "p3_seg82",
      "p2_seg82",
      "p4_seg81",
      "p3_seg81",
      "p2_seg81",
      "p4_seg80",
      "p3_seg80",
      "p2_seg80",
      "p4_seg79",
      "p3_seg79",
      "p2_seg79",
      "p4_seg78",
      "p3_seg78",
      "p2_seg78",
      "p4_seg77",
      "p3_seg77",
      "p2_seg77",
      "p4_seg76",
      "p3_seg76",
      "p2_seg76",
      "p4_seg75",
      "p3_seg75",
      "p2_seg75",
      "p4_seg74",
      "p3_seg74",
      "p2_seg74",
      "p4_seg73",
      "p3_seg73",
      "p2_seg73",
      "p4_seg72",
      "p3_seg72",
      "p2_seg72",
      "p4_seg71",
      "p3_seg71",
      "p2_seg71",
      "p4_seg70",
      "p3_seg70",
      "p2_seg70",
      "p4_seg69",
      "p3_seg69",
      "p2_seg69",
      "p4_seg68",
      "p3_seg68",
      "p2_seg68",
      "p4_seg67",
      "p3_seg67",
      "p2_seg67",
      "p4_seg66",
      "p3_seg66",
      "p2_seg66",
      "p4_seg65",
      "p3_seg65",
      "p2_seg65",
      "p4_seg64",
      "p3_seg64",
      "p2_seg64",
      "p4_seg63",
      "p3_seg63",
      "p2_seg63",
      "p4_seg62",
      "p3_seg62",
      "p2_seg62",
      "p4_seg61",
      "p3_seg61",
      "p2_seg61",
      "p4_seg60",
      "p3_seg60",
      "p2_seg60",
      "p4_seg59",
      "p3_seg59",
      "p2_seg59",
      "p4_seg58",
      "p3_seg58",
      "p2_seg58",
      "p4_seg57",
      "p3_seg57",
      "p2_seg57",
      "p4_seg56",
      "p3_seg56",
      "p2_seg56",
      "p4_seg55",
      "p3_seg55",
      "p2_seg55",
      "p4_seg54",
      "p3_seg54",
      "p2_seg54",
      "p4_seg53",
      "p3_seg53",
      "p2_seg53",
      "p4_seg52",
      "p3_seg52",
      "p2_seg52",
      "p4_seg51",
      "p3_seg51",
      "p2_seg51",
      "p4_seg50",
      "p3_seg50",
      "p2_seg50",
      "p4_seg49",
      "p3_seg49",
      "p2_seg49",
      "p4_seg48",
      "p3_seg48",
      "p2_seg48",
      "p4_seg47",
      "p3_seg47",
      "p2_seg47",
      "p4_seg46",
      "p3_seg46",
      "p2_seg46",
      "p4_seg45",
      "p3_seg45",
      "p2_seg45",
      "p4_seg44",
      "p3_seg44",
      "p2_seg44",
      "p4_seg43",
      "p3_seg43",
      "p2_seg43",
      "p4_seg42",
      "p3_seg42",
      "p2_seg42",
      "p4_seg41",
      "p3_seg41",
      "p2_seg41",
      "p4_seg40",
      "p3_seg40",
      "p2_seg40",
      "p4_seg39",
      "p3_seg39",
      "p2_seg39",
      "p4_seg38",
      "p3_seg38",
      "p2_seg38",
      "p4_seg37",
      "p3_seg37",
      "p2_seg37",
      "p4_seg36",
      "p3_seg36",
      "p2_seg36",
      "p4_seg35",
      "p3_seg35",
      "p2_seg35",
      "p4_seg34",
      "p3_seg34",
      "p2_seg34",
      "p4_seg33",
      "p3_seg33",
      "p2_seg33",
      "p4_seg32",
      "p3_seg32",
      "p2_seg32",
      "p4_seg31",
      "p3_seg31",
      "p2_seg31",
      "p4_seg30",
      "p3_seg30",
      "p2_seg30",
      "p4_seg29",
      "p3_seg29",
      "p2_seg29",
      "p4_seg28",
      "p3_seg28",
      "p2_seg28",
      "p4_seg27",
      "p3_seg27",
      "p2_seg27",
      "p4_seg26",
      "p3_seg26",
      "p2_seg26",
      "p4_seg25",
      "p3_seg25",
      "p2_seg25",
      "p4_seg24",
      "p3_seg24",
      "p2_seg24",
      "p4_seg23",
      "p3_seg23",
      "p2_seg23",
      "p4_seg22",
      "p3_seg22",
      "p2_seg22",
      "p4_seg21",
      "p3_seg21",
      "p2_seg21",
      "p4_seg20",
      "p3_seg20",
      "p2_seg20",
      "p4_seg19",
      "p3_seg19",
      "p2_seg19",
      "p4_seg18",
      "p3_seg18",
      "p2_seg18",
      "p4_seg17",
      "p3_seg17",
      "p2_seg17",
      "p4_seg16",
      "p3_seg16",
      "p2_seg16",
      "p4_seg15",
      "p3_seg15",
      "p2_seg15",
      "p4_seg14",
      "p3_seg14",
      "p2_seg14",
      "p4_seg13",
      "p3_seg13",
      "p2_seg13",
      "p4_seg12",
      "p3_seg12",
      "p2_seg12",
      "p4_seg11",
      "p3_seg11",
      "p2_seg11",
      "p4_seg10",
      "p3_seg10",
      "p2_seg10",
      "p4_seg9",
      "p3_seg9",
      "p2_seg9",
      "p4_seg8",
      "p3_seg8",
      "p2_seg8",
      "p4_seg7",
      "p3_seg7",
      "p2_seg7",
      "p4_seg6",
      "p3_seg6",
      "p2_seg6",
      "p4_seg5",
      "p3_seg5",
      "p2_seg5",
      "p4_seg4",
      "p3_seg4",
      "p2_seg4",
      "p4_seg3",
      "p3_seg3",
      "p2_seg3",
      "p4_seg2",
      "p3_seg2",
      "p2_seg2",
      "p4_seg1",
      "p3_seg1",
      "p2_seg1",
      "ball_seg30",
      "ball_seg29",
      "ball_seg28",
      "ball_seg27",
      "ball_seg26",
      "ball_seg25",
      "ball_seg24",
      "ball_seg23",
      "ball_seg22",
      "ball_seg21",
      "ball_seg20",
      "ball_seg19",
      "ball_seg17",
      "ball_seg16",
      "ball_seg15",
      "ball_seg14",
      "ball_seg13",
      "ball_seg12",
      "ball_seg11",
      "ball_seg10",
      "ball_seg9",
      "ball_seg8",
      "ball_seg7",
      "ball_seg6",
      "ball_seg5",
      "ball_seg4",
      "ball_seg3",
      "ball_seg2",
      "ball_seg1",
      "p1_seg105",
      "p1_seg104",
      "p1_seg103",
      "p1_seg102",
      "p1_seg101",
      "p1_seg100",
      "p1_seg99",
      "p1_seg98",
      "p1_seg97",
      "p1_seg96",
      "p1_seg95",
      "p1_seg94",
      "p1_seg93",
      "p1_seg92",
      "p1_seg91",
      "p1_seg90",
      "p1_seg89",
      "p1_seg88",
      "p1_seg87",
      "p1_seg86",
      "p1_seg85",
      "p1_seg84",
      "p1_seg83",
      "p1_seg82",
      "p1_seg81",
      "p1_seg80",
      "p1_seg79",
      "p1_seg78",
      "p1_seg77",
      "p1_seg76",
      "p1_seg75",
      "p1_seg74",
      "p1_seg73",
      "p1_seg72",
      "p1_seg71",
      "p1_seg70",
      "p1_seg69",
      "p1_seg68",
      "p1_seg67",
      "p1_seg66",
      "p1_seg65",
      "p1_seg64",
      "p1_seg63",
      "p1_seg62",
      "p1_seg61",
      "p1_seg60",
      "p1_seg59",
      "p1_seg58",
      "p1_seg57",
      "p1_seg56",
      "p1_seg55",
      "p1_seg54",
      "p1_seg53",
      "p1_seg52",
      "p1_seg51",
      "p1_seg50",
      "p1_seg49",
      "p1_seg48",
      "p1_seg47",
      "p1_seg46",
      "p1_seg45",
      "p1_seg44",
      "p1_seg43",
      "p1_seg42",
      "p1_seg41",
      "p1_seg40",
      "p1_seg39",
      "p1_seg38",
      "p1_seg37",
      "p1_seg36",
      "p1_seg35",
      "p1_seg34",
      "p1_seg33",
      "p1_seg32",
      "p1_seg31",
      "p1_seg30",
      "p1_seg29",
      "p1_seg28",
      "p1_seg27",
      "p1_seg26",
      "p1_seg25",
      "p1_seg24",
      "p1_seg23",
      "p1_seg22",
      "p1_seg21",
      "p1_seg20",
      "p1_seg19",
      "p1_seg18",
      "p1_seg17",
      "p1_seg16",
      "p1_seg15",
      "p1_seg14",
      "p1_seg13",
      "p1_seg12",
      "p1_seg11",
      "p1_seg10",
      "p1_seg9",
      "p1_seg8",
      "p1_seg7",
      "p1_seg6",
      "p1_seg5",
      "p1_seg4",
      "p1_seg3",
      "p1_seg2",
      "p1_seg1"
    ],
    "fire_events": false,
    "stop_single_events": false,
    "group_elements": false
  },
  {
    "name": "NoTargetBouncer",
    "items": [
      "zCol_Rubber_rightsling",
      "zCol_Rubber_leftsling"
    ],
    "fire_events": true,
    "stop_single_events": false,
    "group_elements": false
  },
  {
    "name": "VR_DisplayBall",
    "items": [
      "p_ball_seg30_vr",
      "p_ball_seg29_vr",
      "p_ball_seg28_vr",
      "p_ball_seg27_vr",
      "p_ball_seg26_vr",
      "p_ball_seg25_vr",
      "p_ball_seg24_vr",
      "p_ball_seg23_vr",
      "p_ball_seg22_vr",
      "p_ball_seg21_vr",
      "p_ball_seg20_vr",
      "p_ball_seg19_vr",
      "p_ball_seg18_vr",
      "p_ball_seg17_vr",
      "p_ball_seg16_vr",
      "p_ball_seg15_vr",
      "p_ball_seg14_vr",
      "p_ball_seg13_vr",
      "p_ball_seg12_vr",
      "p_ball_seg11_vr",
      "p_ball_seg10_vr",
      "p_ball_seg9_vr",
      "p_ball_seg8_vr",
      "p_ball_seg7_vr",
      "p_ball_seg6_vr",
      "p_ball_seg5_vr",
      "p_ball_seg4_vr",
      "p_ball_seg3_vr",
      "p_ball_seg2_vr",
      "p_ball_seg1_vr"
    ],
    "fire_events": false,
    "stop_single_events": false,
    "group_elements": false
  },
  {
    "name": "VR_Display",
    "items": [
      "p_p4_seg120_vr",
      "p_p4_seg119_vr",
      "p_p4_seg118_vr",
      "p_p4_seg117_vr",
      "p_p4_seg116_vr",
      "p_p4_seg115_vr",
      "p_p4_seg114_vr",
      "p_p4_seg113_vr",
      "p_p4_seg112_vr",
      "p_p4_seg111_vr",
      "p_p4_seg110_vr",
      "p_p4_seg109_vr",
      "p_p4_seg108_vr",
      "p_p4_seg107_vr",
      "p_p4_seg106_vr",
      "p_p4_seg105_vr",
      "p_p4_seg104_vr",
      "p_p4_seg103_vr",
      "p_p4_seg102_vr",
      "p_p4_seg101_vr",
      "p_p4_seg100_vr",
      "p_p4_seg99_vr",
      "p_p4_seg98_vr",
      "p_p4_seg97_vr",
      "p_p4_seg96_vr",
      "p_p4_seg95_vr",
      "p_p4_seg94_vr",
      "p_p4_seg93_vr",
      "p_p4_seg92_vr",
      "p_p4_seg91_vr",
      "p_p4_seg90_vr",
      "p_p4_seg89_vr",
      "p_p4_seg88_vr",
      "p_p4_seg87_vr",
      "p_p4_seg86_vr",
      "p_p4_seg85_vr",
      "p_p4_seg84_vr",
      "p_p4_seg83_vr",
      "p_p4_seg82_vr",
      "p_p4_seg81_vr",
      "p_p4_seg80_vr",
      "p_p4_seg79_vr",
      "p_p4_seg78_vr",
      "p_p4_seg77_vr",
      "p_p4_seg76_vr",
      "p_p4_seg75_vr",
      "p_p4_seg74_vr",
      "p_p4_seg73_vr",
      "p_p4_seg72_vr",
      "p_p4_seg71_vr",
      "p_p4_seg70_vr",
      "p_p4_seg69_vr",
      "p_p4_seg68_vr",
      "p_p4_seg67_vr",
      "p_p4_seg66_vr",
      "p_p4_seg65_vr",
      "p_p4_seg64_vr",
      "p_p4_seg63_vr",
      "p_p4_seg62_vr",
      "p_p4_seg61_vr",
      "p_p4_seg60_vr",
      "p_p4_seg59_vr",
      "p_p4_seg58_vr",
      "p_p4_seg57_vr",
      "p_p4_seg56_vr",
      "p_p4_seg55_vr",
      "p_p4_seg54_vr",
      "p_p4_seg53_vr",
      "p_p4_seg52_vr",
      "p_p4_seg51_vr",
      "p_p4_seg50_vr",
      "p_p4_seg49_vr",
      "p_p4_seg48_vr",
      "p_p4_seg47_vr",
      "p_p4_seg46_vr",
      "p_p4_seg45_vr",
      "p_p4_seg44_vr",
      "p_p4_seg43_vr",
      "p_p4_seg42_vr",
      "p_p4_seg41_vr",
      "p_p4_seg40_vr",
      "p_p4_seg39_vr",
      "p_p4_seg38_vr",
      "p_p4_seg37_vr",
      "p_p4_seg36_vr",
      "p_p4_seg35_vr",
      "p_p4_seg34_vr",
      "p_p4_seg33_vr",
      "p_p4_seg32_vr",
      "p_p4_seg31_vr",
      "p_p4_seg30_vr",
      "p_p4_seg29_vr",
      "p_p4_seg28_vr",
      "p_p4_seg27_vr",
      "p_p4_seg26_vr",
      "p_p4_seg25_vr",
      "p_p4_seg24_vr",
      "p_p4_seg23_vr",
      "p_p4_seg22_vr",
      "p_p4_seg21_vr",
      "p_p4_seg20_vr",
      "p_p4_seg19_vr",
      "p_p4_seg18_vr",
      "p_p4_seg17_vr",
      "p_p4_seg16_vr",
      "p_p4_seg15_vr",
      "p_p4_seg14_vr",
      "p_p4_seg13_vr",
      "p_p4_seg12_vr",
      "p_p4_seg11_vr",
      "p_p4_seg10_vr",
      "p_p4_seg9_vr",
      "p_p4_seg8_vr",
      "p_p4_seg7_vr",
      "p_p4_seg6_vr",
      "p_p4_seg5_vr",
      "p_p4_seg4_vr",
      "p_p4_seg3_vr",
      "p_p4_seg2_vr",
      "p_p4_seg1_vr",
      "p_p3_seg120_vr",
      "p_p3_seg119_vr",
      "p_p3_seg118_vr",
      "p_p3_seg117_vr",
      "p_p3_seg116_vr",
      "p_p3_seg115_vr",
      "p_p3_seg114_vr",
      "p_p3_seg113_vr",
      "p_p3_seg112_vr",
      "p_p3_seg111_vr",
      "p_p3_seg110_vr",
      "p_p3_seg109_vr",
      "p_p3_seg108_vr",
      "p_p3_seg107_vr",
      "p_p3_seg106_vr",
      "p_p3_seg105_vr",
      "p_p3_seg104_vr",
      "p_p3_seg103_vr",
      "p_p3_seg102_vr",
      "p_p3_seg101_vr",
      "p_p3_seg100_vr",
      "p_p3_seg99_vr",
      "p_p3_seg98_vr",
      "p_p3_seg97_vr",
      "p_p3_seg96_vr",
      "p_p3_seg95_vr",
      "p_p3_seg94_vr",
      "p_p3_seg93_vr",
      "p_p3_seg92_vr",
      "p_p3_seg91_vr",
      "p_p3_seg90_vr",
      "p_p3_seg89_vr",
      "p_p3_seg88_vr",
      "p_p3_seg87_vr",
      "p_p3_seg86_vr",
      "p_p3_seg85_vr",
      "p_p3_seg84_vr",
      "p_p3_seg83_vr",
      "p_p3_seg82_vr",
      "p_p3_seg81_vr",
      "p_p3_seg80_vr",
      "p_p3_seg79_vr",
      "p_p3_seg78_vr",
      "p_p3_seg77_vr",
      "p_p3_seg76_vr",
      "p_p3_seg75_vr",
      "p_p3_seg74_vr",
      "p_p3_seg73_vr",
      "p_p3_seg72_vr",
      "p_p3_seg71_vr",
      "p_p3_seg70_vr",
      "p_p3_seg69_vr",
      "p_p3_seg68_vr",
      "p_p3_seg67_vr",
      "p_p3_seg66_vr",
      "p_p3_seg65_vr",
      "p_p3_seg64_vr",
      "p_p3_seg63_vr",
      "p_p3_seg62_vr",
      "p_p3_seg61_vr",
      "p_p3_seg60_vr",
      "p_p3_seg59_vr",
      "p_p3_seg58_vr",
      "p_p3_seg57_vr",
      "p_p3_seg56_vr",
      "p_p3_seg55_vr",
      "p_p3_seg54_vr",
      "p_p3_seg53_vr",
      "p_p3_seg52_vr",
      "p_p3_seg51_vr",
      "p_p3_seg50_vr",
      "p_p3_seg49_vr",
      "p_p3_seg48_vr",
      "p_p3_seg47_vr",
      "p_p3_seg46_vr",
      "p_p3_seg45_vr",
      "p_p3_seg44_vr",
      "p_p3_seg43_vr",
      "p_p3_seg42_vr",
      "p_p3_seg41_vr",
      "p_p3_seg40_vr",
      "p_p3_seg39_vr",
      "p_p3_seg38_vr",
      "p_p3_seg37_vr",
      "p_p3_seg36_vr",
      "p_p3_seg35_vr",
      "p_p3_seg34_vr",
      "p_p3_seg33_vr",
      "p_p3_seg32_vr",
      "p_p3_seg31_vr",
      "p_p3_seg30_vr",
      "p_p3_seg29_vr",
      "p_p3_seg28_vr",
      "p_p3_seg27_vr",
      "p_p3_seg26_vr",
      "p_p3_seg25_vr",
      "p_p3_seg24_vr",
      "p_p3_seg23_vr",
      "p_p3_seg22_vr",
      "p_p3_seg21_vr",
      "p_p3_seg20_vr",
      "p_p3_seg19_vr",
      "p_p3_seg18_vr",
      "p_p3_seg17_vr",
      "p_p3_seg16_vr",
      "p_p3_seg15_vr",
      "p_p3_seg14_vr",
      "p_p3_seg13_vr",
      "p_p3_seg12_vr",
      "p_p3_seg11_vr",
      "p_p3_seg10_vr",
      "p_p3_seg9_vr",
      "p_p3_seg8_vr",
      "p_p3_seg7_vr",
      "p_p3_seg6_vr",
      "p_p3_seg5_vr",
      "p_p3_seg4_vr",
      "p_p3_seg3_vr",
      "p_p3_seg2_vr",
      "p_p3_seg1_vr",
      "p_p2_seg120_vr",
      "p_p2_seg119_vr",
      "p_p2_seg118_vr",
      "p_p2_seg117_vr",
      "p_p2_seg116_vr",
      "p_p2_seg115_vr",
      "p_p2_seg114_vr",
      "p_p2_seg113_vr",
      "p_p2_seg112_vr",
      "p_p2_seg111_vr",
      "p_p2_seg110_vr",
      "p_p2_seg109_vr",
      "p_p2_seg108_vr",
      "p_p2_seg107_vr",
      "p_p2_seg106_vr",
      "p_p2_seg105_vr",
      "p_p2_seg104_vr",
      "p_p2_seg103_vr",
      "p_p2_seg102_vr",
      "p_p2_seg101_vr",
      "p_p2_seg100_vr",
      "p_p2_seg99_vr",
      "p_p2_seg98_vr",
      "p_p2_seg97_vr",
      "p_p2_seg96_vr",
      "p_p2_seg95_vr",
      "p_p2_seg94_vr",
      "p_p2_seg93_vr",
      "p_p2_seg92_vr",
      "p_p2_seg91_vr",
      "p_p2_seg90_vr",
      "p_p2_seg89_vr",
      "p_p2_seg88_vr",
      "p_p2_seg87_vr",
      "p_p2_seg86_vr",
      "p_p2_seg85_vr",
      "p_p2_seg84_vr",
      "p_p2_seg83_vr",
      "p_p2_seg82_vr",
      "p_p2_seg81_vr",
      "p_p2_seg80_vr",
      "p_p2_seg79_vr",
      "p_p2_seg78_vr",
      "p_p2_seg77_vr",
      "p_p2_seg76_vr",
      "p_p2_seg75_vr",
      "p_p2_seg74_vr",
      "p_p2_seg73_vr",
      "p_p2_seg72_vr",
      "p_p2_seg71_vr",
      "p_p2_seg70_vr",
      "p_p2_seg69_vr",
      "p_p2_seg68_vr",
      "p_p2_seg67_vr",
      "p_p2_seg66_vr",
      "p_p2_seg65_vr",
      "p_p2_seg64_vr",
      "p_p2_seg63_vr",
      "p_p2_seg62_vr",
      "p_p2_seg61_vr",
      "p_p2_seg60_vr",
      "p_p2_seg59_vr",
      "p_p2_seg58_vr",
      "p_p2_seg57_vr",
      "p_p2_seg56_vr",
      "p_p2_seg55_vr",
      "p_p2_seg54_vr",
      "p_p2_seg53_vr",
      "p_p2_seg52_vr",
      "p_p2_seg51_vr",
      "p_p2_seg50_vr",
      "p_p2_seg49_vr",
      "p_p2_seg48_vr",
      "p_p2_seg47_vr",
      "p_p2_seg46_vr",
      "p_p2_seg45_vr",
      "p_p2_seg44_vr",
      "p_p2_seg43_vr",
      "p_p2_seg42_vr",
      "p_p2_seg41_vr",
      "p_p2_seg40_vr",
      "p_p2_seg39_vr",
      "p_p2_seg38_vr",
      "p_p2_seg37_vr",
      "p_p2_seg36_vr",
      "p_p2_seg35_vr",
      "p_p2_seg34_vr",
      "p_p2_seg33_vr",
      "p_p2_seg32_vr",
      "p_p2_seg31_vr",
      "p_p2_seg30_vr",
      "p_p2_seg29_vr",
      "p_p2_seg28_vr",
      "p_p2_seg27_vr",
      "p_p2_seg26_vr",
      "p_p2_seg25_vr",
      "p_p2_seg24_vr",
      "p_p2_seg23_vr",
      "p_p2_seg22_vr",
      "p_p2_seg21_vr",
      "p_p2_seg20_vr",
      "p_p2_seg19_vr",
      "p_p2_seg18_vr",
      "p_p2_seg17_vr",
      "p_p2_seg16_vr",
      "p_p2_seg15_vr",
      "p_p2_seg14_vr",
      "p_p2_seg13_vr",
      "p_p2_seg12_vr",
      "p_p2_seg11_vr",
      "p_p2_seg10_vr",
      "p_p2_seg9_vr",
      "p_p2_seg8_vr",
      "p_p2_seg7_vr",
      "p_p2_seg6_vr",
      "p_p2_seg5_vr",
      "p_p2_seg4_vr",
      "p_p2_seg3_vr",
      "p_p2_seg2_vr",
      "p_p2_seg1_vr",
      "p_p1_seg120_vr",
      "p_p1_seg119_vr",
      "p_p1_seg118_vr",
      "p_p1_seg117_vr",
      "p_p1_seg116_vr",
      "p_p1_seg115_vr",
      "p_p1_seg114_vr",
      "p_p1_seg113_vr",
      "p_p1_seg112_vr",
      "p_p1_seg111_vr",
      "p_p1_seg110_vr",
      "p_p1_seg109_vr",
      "p_p1_seg108_vr",
      "p_p1_seg107_vr",
      "p_p1_seg106_vr",
      "p_p1_seg105_vr",
      "p_p1_seg104_vr",
      "p_p1_seg103_vr",
      "p_p1_seg102_vr",
      "p_p1_seg101_vr",
      "p_p1_seg100_vr",
      "p_p1_seg99_vr",
      "p_p1_seg98_vr",
      "p_p1_seg97_vr",
      "p_p1_seg96_vr",
      "p_p1_seg95_vr",
      "p_p1_seg94_vr",
      "p_p1_seg93_vr",
      "p_p1_seg92_vr",
      "p_p1_seg91_vr",
      "p_p1_seg90_vr",
      "p_p1_seg89_vr",
      "p_p1_seg88_vr",
      "p_p1_seg87_vr",
      "p_p1_seg86_vr",
      "p_p1_seg85_vr",
      "p_p1_seg84_vr",
      "p_p1_seg83_vr",
      "p_p1_seg82_vr",
      "p_p1_seg81_vr",
      "p_p1_seg80_vr",
      "p_p1_seg79_vr",
      "p_p1_seg78_vr",
      "p_p1_seg77_vr",
      "p_p1_seg76_vr",
      "p_p1_seg75_vr",
      "p_p1_seg74_vr",
      "p_p1_seg73_vr",
      "p_p1_seg72_vr",
      "p_p1_seg71_vr",
      "p_p1_seg70_vr",
      "p_p1_seg69_vr",
      "p_p1_seg68_vr",
      "p_p1_seg67_vr",
      "p_p1_seg66_vr",
      "p_p1_seg65_vr",
      "p_p1_seg64_vr",
      "p_p1_seg63_vr",
      "p_p1_seg62_vr",
      "p_p1_seg61_vr",
      "p_p1_seg60_vr",
      "p_p1_seg59_vr",
      "p_p1_seg58_vr",
      "p_p1_seg57_vr",
      "p_p1_seg56_vr",
      "p_p1_seg55_vr",
      "p_p1_seg54_vr",
      "p_p1_seg53_vr",
      "p_p1_seg52_vr",
      "p_p1_seg51_vr",
      "p_p1_seg50_vr",
      "p_p1_seg49_vr",
      "p_p1_seg48_vr",
      "p_p1_seg47_vr",
      "p_p1_seg46_vr",
      "p_p1_seg45_vr",
      "p_p1_seg44_vr",
      "p_p1_seg43_vr",
      "p_p1_seg42_vr",
      "p_p1_seg41_vr",
      "p_p1_seg40_vr",
      "p_p1_seg39_vr",
      "p_p1_seg38_vr",
      "p_p1_seg37_vr",
      "p_p1_seg36_vr",
      "p_p1_seg35_vr",
      "p_p1_seg34_vr",
      "p_p1_seg33_vr",
      "p_p1_seg32_vr",
      "p_p1_seg31_vr",
      "p_p1_seg30_vr",
      "p_p1_seg29_vr",
      "p_p1_seg28_vr",
      "p_p1_seg27_vr",
      "p_p1_seg26_vr",
      "p_p1_seg25_vr",
      "p_p1_seg24_vr",
      "p_p1_seg23_vr",
      "p_p1_seg22_vr",
      "p_p1_seg21_vr",
      "p_p1_seg20_vr",
      "p_p1_seg19_vr",
      "p_p1_seg18_vr",
      "p_p1_seg17_vr",
      "p_p1_seg16_vr",
      "p_p1_seg15_vr",
      "p_p1_seg14_vr",
      "p_p1_seg13_vr",
      "p_p1_seg12_vr",
      "p_p1_seg11_vr",
      "p_p1_seg10_vr",
      "p_p1_seg9_vr",
      "p_p1_seg8_vr",
      "p_p1_seg7_vr",
      "p_p1_seg6_vr",
      "p_p1_seg5_vr",
      "p_p1_seg4_vr",
      "p_p1_seg3_vr",
      "p_p1_seg2_vr",
      "p_p1_seg1_vr"
    ],
    "fire_events": false,
    "stop_single_events": false,
    "group_elements": false
  },
  {
    "name": "VR_Backglass",
    "items": [
      "BGTranslite",
      "BGDisplayBall",
      "BGDisplay"
    ],
    "fire_events": false,
    "stop_single_events": false,
    "group_elements": false
  },
  {
    "name": "VR_Flashers",
    "items": [
      "F_LBG12_",
      "F_LBG16_",
      "F_LBG15_",
      "F_LBG14_",
      "F_LBG13_",
      "F_LBG11_",
      "F_LBG10_",
      "F_LBG09_",
      "F_LBG08_",
      "F_LBG07_",
      "F_LBG06_",
      "F_LBG05_",
      "F_LBG04_",
      "F_LBG03_",
      "F_LBG02_d",
      "F_LBG02_c",
      "F_LBG02_b",
      "F_LBG02_a",
      "F_LBG01_d",
      "F_LBG01_c",
      "F_LBG01_b",
      "F_LBG01_a"
    ],
    "fire_events": false,
    "stop_single_events": false,
    "group_elements": false
  }
]